bot_creator/__init__.py
bot_creator/creator.py
discord_bot_creator-0.1.2.dist-info/License.txt
discord_bot_creator-0.1.2.dist-info/METADATA
discord_bot_creator-0.1.2.dist-info/WHEEL
discord_bot_creator-0.1.2.dist-info/top_level.txt
discord_bot_creator-0.1.2.dist-info/RECORD
