Metadata-Version: 2.1
Name: discord-bot-creator
Version: 0.1.2
Author: CedricXBG
Author-email: levistimmy@gmail.com
License: MIT
Classifier: Programming Language :: Python :: 3
Classifier: License :: OSI Approved :: MIT License
Classifier: Operating System :: OS Independent
License-File: License.txt
